codegate/__init__.py
codegate/cli.py
codegate/analysis/__init__.py
codegate/analysis/crawler.py
codegate/analysis/prober.py
codegate/analysis/resolver.py
codegate/engine/__init__.py
codegate/engine/gatekeeper.py
codegate/engine/orchestrator.py
codegate/engine/sandbox.py
codegate_cli-0.1.5.dist-info/METADATA
codegate_cli-0.1.5.dist-info/WHEEL
codegate_cli-0.1.5.dist-info/entry_points.txt
codegate_cli-0.1.5.dist-info/top_level.txt
codegate_cli-0.1.5.dist-info/RECORD
