Metadata-Version: 2.1
Name: codegate-cli
Version: 0.1.5
Summary: The Supply Chain Firewall for AI Agents. Detects hallucinated dependencies.
Home-page: https://github.com/dariomonopoli-dev/codegate-cli
Author: Dario Monopoli
Author-email: jerryscout71@gmail.com
License: UNKNOWN
Platform: UNKNOWN
Classifier: Programming Language :: Python :: 3
Classifier: License :: OSI Approved :: MIT License
Classifier: Operating System :: OS Independent
Classifier: Topic :: Security
Classifier: Intended Audience :: Developers
Requires-Python: >=3.8
Requires-Dist: requests>=2.31.0
Requires-Dist: rich>=13.7.0
Requires-Dist: openai>=1.12.0
